Workbook
Name in_feedstock_carbon: 'Inputs'!$B$2
Name in_feedstock_yield: 'Inputs'!$B$3
Name in_feedstock_cost: 'Inputs'!$B$4
Name in_plant_capacity: 'Inputs'!$B$5
Name in_gas_consumption: 'Inputs'!$B$6
Name in_line_conversion: 'Inputs'!$B$7
Name in_biochar_rate: 'Inputs'!$B$8
Name in_carbon_price: 'Inputs'!$B$9
Name in_credit_multiplier: 'Inputs'!$B$10
Name out_gas_pct: 'Outputs'!$B$2
Name out_gas_mwh: 'Outputs'!$B$3
Name out_gypsum_pct: 'Outputs'!$B$4
Name out_gypsum_tonnes: 'Outputs'!$B$5
Name out_net_carbon: 'Outputs'!$B$6
Name out_cdr_tonnes: 'Outputs'!$B$7
Name out_capex: 'Outputs'!$B$8
Name out_opex: 'Outputs'!$B$9
Name out_unit_cost: 'Outputs'!$B$10
Name out_net_cash: 'Outputs'!$B$11
Name out_payback: 'Outputs'!$B$12
Name out_npv: 'Outputs'!$B$13
Name int_feedstock_tonnes: 'Internal'!$B$2
Name int_converted_output: 'Internal'!$B$3
Name int_gas_savings: 'Internal'!$B$4
Name int_carbon_revenue: 'Internal'!$B$5

Sheet Inputs
A1: INPUT | B1: VALUE | C1: UNIT
A2: Feedstock carbon factor | B2: 1 | C2: multiplier
A3: Feedstock yield factor | B3: 1 | C3: multiplier
A4: Feedstock delivered cost | B4: 180 | C4: GBP/tonne
A5: Annual plant capacity | B5: 5000000 | C5: m2/yr
A6: Current gas consumption | B6: 9.5 | C6: kWh/m2
A7: Line conversion level | B7: 40 | C7: percent
A8: Biochar inclusion rate | B8: 15 | C8: percent
A9: Carbon credit price | B9: 120 | C9: GBP/tCO2e
A10: Credit mode multiplier | B10: 1 | C10: multiplier

Sheet Calculations
A1: INTERNAL MODEL, NEVER EXPOSED TO THE CLIENT
A2: Conversion share | B2: =in_line_conversion/100
A3: Biochar share | B3: =in_biochar_rate/100
A4: Baseline carbon | B4: =6.4
A5: Converted output | B5: =in_plant_capacity*B2
A6: Feedstock tonnes | B6: =in_plant_capacity*B2*B3*0.00065*(1/in_feedstock_yield)
A7: Opex feedstock | B7: =B6*in_feedstock_cost
A8: Opex fixed | B8: =165000*(in_plant_capacity/5000000)
A9: Gas savings value | B9: =(in_plant_capacity*in_gas_consumption*B2*0.45/1000)*38
A10: Carbon revenue | B10: =(in_plant_capacity*B2*B3*0.0091*in_feedstock_carbon)*in_carbon_price*in_credit_multiplier

Sheet Outputs
A1: OUTPUT | B1: VALUE | C1: UNIT
A2: Gas displacement pct | B2: =MIN(100,Calculations!B2*62) | C2: percent
A3: Gas displacement MWh | B3: =in_plant_capacity*in_gas_consumption*Calculations!B2*0.45/1000 | C3: MWh/yr
A4: Gypsum saved pct | B4: =MIN(100,Calculations!B3*145) | C4: percent
A5: Gypsum saved tonnes | B5: =in_plant_capacity*Calculations!B2*Calculations!B3*0.052*in_feedstock_yield | C5: tonnes/yr
A6: Net embodied carbon | B6: =Calculations!B4-(Calculations!B2*Calculations!B3*22*in_feedstock_carbon) | C6: kgCO2e/m2
A7: Annual CO2 removed | B7: =in_plant_capacity*Calculations!B2*Calculations!B3*0.0091*in_feedstock_carbon | C7: tonnes/yr
A8: Capex | B8: =2600000*(in_plant_capacity/5000000)*(0.6+Calculations!B2*0.4) | C8: GBP
A9: Opex | B9: =Calculations!B7+Calculations!B8 | C9: GBP/yr
A10: Unit cost | B10: =IF(Calculations!B5>0,(Calculations!B7+Calculations!B8)/Calculations!B5,0) | C10: GBP/m2
A11: Net annual cash flow | B11: =Calculations!B9+Calculations!B10-(Calculations!B7+Calculations!B8) | C11: GBP/yr
A12: Payback years | B12: =IF(out_net_cash>0,out_capex/out_net_cash,-1) | C12: years
A13: NPV 10yr at 8pct | B13: =-out_capex+out_net_cash*((1-(1.08^-10))/0.08) | C13: GBP

Sheet Internal
A1: INTERNAL OUTPUT | B1: VALUE
A2: Feedstock tonnes | B2: =Calculations!B6
A3: Converted output | B3: =Calculations!B5
A4: Gas savings value | B4: =Calculations!B9
A5: Carbon revenue | B5: =Calculations!B10
